{
    "frameTimeCount": 1.0000000521540642,
    "bones": [
        {
            "boneId": 1000,
            "frameType": 3,
            "startTime": 0.99609375,
            "frames": {
                "frames": [
                    {
                        "position": [
                            0,
                            0.09228515625,
                            0
                        ]
                    },
                    {
                        "position": [
                            0,
                            0.09228515625,
                            0
                        ]
                    }
                ],
                "lastFrameTime": 1.0000000521540642
            },
            "direction": [
                -0.90234375,
                0.91943359375,
                -1.15771484375,
                -0.9990234375
            ]
        },
        {
            "boneId": 1045,
            "frameType": 1,
            "startTime": 0.99609375,
            "frames": {
                "frames": [
                    {
                        "quat": [
                            1,
                            1,
                            -0.99951171875,
                            1
                        ]
                    }
                ],
                "lastFrameTime": 1.0000000521540642
            }
        },
        {
            "boneId": 1077,
            "frameType": 3,
            "startTime": 0.99609375,
            "frames": {
                "frames": [
                    {
                        "position": [
                            0,
                            -0.09326171875,
                            0
                        ]
                    },
                    {
                        "position": [
                            0,
                            -0.09326171875,
                            0
                        ]
                    }
                ],
                "lastFrameTime": 1.0000000521540642
            },
            "direction": [
                0.15478515625,
                -0.123046875,
                -1.95556640625,
                -0.3662109375
            ]
        },
        {
            "boneId": 1056,
            "frameType": 1,
            "startTime": 0.99609375,
            "frames": {
                "frames": [
                    {
                        "quat": [
                            0,
                            0.25390625,
                            0,
                            1.98388671875
                        ]
                    }
                ],
                "lastFrameTime": 1.0000000521540642
            }
        },
        {
            "boneId": 1073,
            "frameType": 1,
            "startTime": 0.99609375,
            "frames": {
                "frames": [
                    {
                        "quat": [
                            0.04345703125,
                            0.5537109375,
                            0.2158203125,
                            1.9091796875
                        ]
                    }
                ],
                "lastFrameTime": 1.0000000521540642
            }
        },
        {
            "boneId": 1078,
            "frameType": 1,
            "startTime": 0.99609375,
            "frames": {
                "frames": [
                    {
                        "quat": [
                            0.0419921875,
                            -1.4072265625,
                            0.04296875,
                            1.41943359375
                        ]
                    }
                ],
                "lastFrameTime": 1.0000000521540642
            }
        },
        {
            "boneId": 1023,
            "frameType": 3,
            "startTime": 0.99609375,
            "frames": {
                "frames": [
                    {
                        "position": [
                            0,
                            0.09375,
                            0
                        ]
                    },
                    {
                        "position": [
                            0,
                            0.09375,
                            0
                        ]
                    }
                ],
                "lastFrameTime": 1.0000000521540642
            },
            "direction": [
                0.24560546875,
                0.626953125,
                -1.880859375,
                0.0830078125
            ]
        },
        {
            "boneId": 1002,
            "frameType": 1,
            "startTime": 0.99609375,
            "frames": {
                "frames": [
                    {
                        "quat": [
                            0,
                            0.40625,
                            0,
                            1.95849609375
                        ]
                    }
                ],
                "lastFrameTime": 1.0000000521540642
            }
        },
        {
            "boneId": 1019,
            "frameType": 1,
            "startTime": 0.99609375,
            "frames": {
                "frames": [
                    {
                        "quat": [
                            0.3818359375,
                            0.27978515625,
                            -0.36083984375,
                            1.9091796875
                        ]
                    }
                ],
                "lastFrameTime": 1.0000000521540642
            }
        },
        {
            "boneId": 1024,
            "frameType": 1,
            "startTime": 0.99609375,
            "frames": {
                "frames": [
                    {
                        "quat": [
                            -0.07861328125,
                            -1.37890625,
                            -0.0029296875,
                            1.4462890625
                        ]
                    }
                ],
                "lastFrameTime": 1.0000000521540642
            }
        },
        {
            "boneId": 1094,
            "frameType": 1,
            "startTime": 0.99609375,
            "frames": {
                "frames": [
                    {
                        "quat": [
                            0.94189453125,
                            1.1328125,
                            -0.935546875,
                            0.9765625
                        ]
                    }
                ],
                "lastFrameTime": 1.0000000521540642
            }
        },
        {
            "boneId": 1095,
            "frameType": 1,
            "startTime": 0.99609375,
            "frames": {
                "frames": [
                    {
                        "quat": [
                            0.0166015625,
                            -0.05859375,
                            0.013671875,
                            1.9990234375
                        ]
                    }
                ],
                "lastFrameTime": 1.0000000521540642
            }
        },
        {
            "boneId": 1096,
            "frameType": 1,
            "startTime": 0.99609375,
            "frames": {
                "frames": [
                    {
                        "quat": [
                            0.015625,
                            -0.05859375,
                            0.01513671875,
                            1.9990234375
                        ]
                    }
                ],
                "lastFrameTime": 1.0000000521540642
            }
        },
        {
            "boneId": 1040,
            "frameType": 1,
            "startTime": 0.99609375,
            "frames": {
                "frames": [
                    {
                        "quat": [
                            0.4521484375,
                            0.06298828125,
                            0.1123046875,
                            1.94384765625
                        ]
                    }
                ],
                "lastFrameTime": 1.0000000521540642
            }
        },
        {
            "boneId": 1001,
            "frameType": 1,
            "startTime": 0.99609375,
            "frames": {
                "frames": [
                    {
                        "quat": [
                            0.83251953125,
                            0.3154296875,
                            -0.28369140625,
                            1.76806640625
                        ]
                    }
                ],
                "lastFrameTime": 1.0000000521540642
            }
        },
        {
            "boneId": 1003,
            "frameType": 3,
            "startTime": 0.99609375,
            "frames": {
                "frames": [
                    {
                        "position": [
                            0.1318359375,
                            0.04541015625,
                            0.00146484375
                        ]
                    },
                    {
                        "position": [
                            0.1318359375,
                            0.04541015625,
                            0.00146484375
                        ]
                    }
                ],
                "lastFrameTime": 1.0000000521540642
            },
            "direction": [
                1.427734375,
                1.3984375,
                0.0556640625,
                0.0556640625
            ]
        },
        {
            "boneId": 1039,
            "frameType": 1,
            "startTime": 0.99609375,
            "frames": {
                "frames": [
                    {
                        "quat": [
                            -0.91943359375,
                            0.7822265625,
                            0.74267578125,
                            1.4111328125
                        ]
                    }
                ],
                "lastFrameTime": 1.0000000521540642
            }
        },
        {
            "boneId": 1020,
            "frameType": 1,
            "startTime": 0.99609375,
            "frames": {
                "frames": [
                    {
                        "quat": [
                            0,
                            0.162109375,
                            0,
                            1.99365234375
                        ]
                    }
                ],
                "lastFrameTime": 1.0000000521540642
            }
        },
        {
            "boneId": 1021,
            "frameType": 1,
            "startTime": 0.99609375,
            "frames": {
                "frames": [
                    {
                        "quat": [
                            1.27880859375,
                            0.048828125,
                            0.32177734375,
                            1.5029296875
                        ]
                    }
                ],
                "lastFrameTime": 1.0000000521540642
            }
        },
        {
            "boneId": 1057,
            "frameType": 3,
            "startTime": 0.99609375,
            "frames": {
                "frames": [
                    {
                        "position": [
                            0.1318359375,
                            -0.044921875,
                            0.00146484375
                        ]
                    },
                    {
                        "position": [
                            0.1318359375,
                            -0.044921875,
                            0.00146484375
                        ]
                    }
                ],
                "lastFrameTime": 1.0000000521540642
            },
            "direction": [
                -1.4013671875,
                1.42626953125,
                -0.00927734375,
                0.00830078125
            ]
        },
        {
            "boneId": 1093,
            "frameType": 1,
            "startTime": 0.99609375,
            "frames": {
                "frames": [
                    {
                        "quat": [
                            1.36328125,
                            0.69873046875,
                            -0.2607421875,
                            1.2587890625
                        ]
                    }
                ],
                "lastFrameTime": 1.0000000521540642
            }
        },
        {
            "boneId": 1074,
            "frameType": 1,
            "startTime": 0.99609375,
            "frames": {
                "frames": [
                    {
                        "quat": [
                            0,
                            0.53857421875,
                            0,
                            1.92626953125
                        ]
                    }
                ],
                "lastFrameTime": 1.0000000521540642
            }
        },
        {
            "boneId": 1075,
            "frameType": 1,
            "startTime": 0.99609375,
            "frames": {
                "frames": [
                    {
                        "quat": [
                            -1.119140625,
                            0.39013671875,
                            -0.0263671875,
                            1.6103515625
                        ]
                    }
                ],
                "lastFrameTime": 1.0000000521540642
            }
        }
    ],
    "unknown5": "00004040",
    "entry": [
        {
            "time": 0.0010000000474974513,
            "unknown": "00000000",
            "unknown2": "00000000",
            "CommandName": "",
            "unknown3": "01000000",
            "unknown6": 1.4643568952194338e-42,
            "particleName": "blood4",
            "particlePosition": [
                -0.07030709832906723,
                -0.03794439882040024,
                -0.07794920355081558,
                0.26764199137687683,
                0.13932399451732635,
                -0.6394829750061035,
                0.7071189880371094
            ],
            "unknown5": "00000000000000000000000000000000000000000000000000000000000000000000000000000000",
            "unknownCommandRemain": "\u0000\u0000\u0000\u0000\u0000\u0000\u0000\u0000\u0000\u0000\u0000\u0000\u0000\u0000\u0000\u0000\u0000\u0000\u0000\u0000\u0000\u0000\u0000\u0000\u0000\u0000\u0000\u0000\u0000\u0000\u0000\u0000\u0000\u0000\u0000\u0000\u0000\u0000\u0000\u0000\u0000\u0000\u0000\u0000\u0000\u0000\u0000\u0000\u0000\u0000\u0000\u0000\u0000\u0000\u0000\u0000\u0000\u0000\u0000\u0000\u0000\u0000\u0000\u0000",
            "unknownParticleName": "\u0000\u0000"
        }
    ]
}