{
    "frameTimeCount": 30,
    "bones": [
        {
            "boneId": 1000,
            "frameType": 3,
            "startTime": 30,
            "frames": {
                "frames": [
                    {
                        "position": [
                            0,
                            0.9990234375,
                            0
                        ]
                    },
                    {
                        "position": [
                            0,
                            0.9990234375,
                            0
                        ]
                    }
                ],
                "lastFrameTime": 30
            },
            "direction": [
                0,
                -1.41357421875,
                0,
                1.4140625
            ]
        },
        {
            "boneId": 1045,
            "frameType": 1,
            "startTime": 30,
            "frames": {
                "frames": [
                    {
                        "quat": [
                            1.2822265625,
                            1.33544921875,
                            -0.52685546875,
                            0.54296875
                        ]
                    }
                ],
                "lastFrameTime": 30
            }
        },
        {
            "boneId": 1023,
            "frameType": 3,
            "startTime": 30,
            "frames": {
                "frames": [
                    {
                        "position": [
                            0,
                            0.09375,
                            0
                        ]
                    },
                    {
                        "position": [
                            0,
                            0.09375,
                            0
                        ]
                    }
                ],
                "lastFrameTime": 30
            },
            "direction": [
                0.3037109375,
                0.39306640625,
                -1.92041015625,
                0.25146484375
            ]
        },
        {
            "boneId": 1002,
            "frameType": 1,
            "startTime": 30,
            "frames": {
                "frames": [
                    {
                        "quat": [
                            0,
                            0.43603515625,
                            0,
                            1.95166015625
                        ]
                    }
                ],
                "lastFrameTime": 30
            }
        },
        {
            "boneId": 1019,
            "frameType": 1,
            "startTime": 30,
            "frames": {
                "frames": [
                    {
                        "quat": [
                            0.0302734375,
                            -0.04296875,
                            -0.2158203125,
                            1.98779296875
                        ]
                    }
                ],
                "lastFrameTime": 30
            }
        },
        {
            "boneId": 1024,
            "frameType": 1,
            "startTime": 30,
            "frames": {
                "frames": [
                    {
                        "quat": [
                            -0.0205078125,
                            -1.43017578125,
                            -0.01171875,
                            1.3974609375
                        ]
                    }
                ],
                "lastFrameTime": 30
            }
        },
        {
            "boneId": 1077,
            "frameType": 3,
            "startTime": 30,
            "frames": {
                "frames": [
                    {
                        "position": [
                            0,
                            -0.09326171875,
                            0
                        ]
                    },
                    {
                        "position": [
                            0,
                            -0.09326171875,
                            0
                        ]
                    }
                ],
                "lastFrameTime": 30
            },
            "direction": [
                0.18505859375,
                -0.1884765625,
                -1.9658203125,
                -0.25
            ]
        },
        {
            "boneId": 1056,
            "frameType": 1,
            "startTime": 30,
            "frames": {
                "frames": [
                    {
                        "quat": [
                            0,
                            0.611328125,
                            0,
                            1.904296875
                        ]
                    }
                ],
                "lastFrameTime": 30
            }
        },
        {
            "boneId": 1073,
            "frameType": 1,
            "startTime": 30,
            "frames": {
                "frames": [
                    {
                        "quat": [
                            -0.158203125,
                            -0.39013671875,
                            0.232421875,
                            1.94140625
                        ]
                    }
                ],
                "lastFrameTime": 30
            }
        },
        {
            "boneId": 1078,
            "frameType": 1,
            "startTime": 30,
            "frames": {
                "frames": [
                    {
                        "quat": [
                            0.02294921875,
                            -1.416015625,
                            0.02294921875,
                            1.41162109375
                        ]
                    }
                ],
                "lastFrameTime": 30
            }
        },
        {
            "boneId": 1094,
            "frameType": 1,
            "startTime": 0,
            "frames": {
                "frames": [
                    {
                        "time": 0,
                        "quat": [
                            1.310546875,
                            1.28076171875,
                            -0.50634765625,
                            0.6201171875
                        ]
                    },
                    {
                        "time": 14.00390625,
                        "quat": [
                            1.32763671875,
                            1.2587890625,
                            -0.46044921875,
                            0.6640625
                        ]
                    },
                    {
                        "time": 15.99609375,
                        "quat": [
                            1.310546875,
                            1.28076171875,
                            -0.50634765625,
                            0.6201171875
                        ]
                    }
                ],
                "lastFrameTime": 15.99609375
            }
        },
        {
            "boneId": 1095,
            "frameType": 1,
            "startTime": 0,
            "frames": {
                "frames": [
                    {
                        "time": 0,
                        "quat": [
                            0.30859375,
                            -0.046875,
                            0.02978515625,
                            1.97509765625
                        ]
                    },
                    {
                        "time": 14.00390625,
                        "quat": [
                            0.3095703125,
                            0.03857421875,
                            0.01611328125,
                            1.9755859375
                        ]
                    },
                    {
                        "time": 15.99609375,
                        "quat": [
                            0.30859375,
                            -0.046875,
                            0.02978515625,
                            1.97509765625
                        ]
                    }
                ],
                "lastFrameTime": 15.99609375
            }
        },
        {
            "boneId": 1096,
            "frameType": 1,
            "startTime": 30,
            "frames": {
                "frames": [
                    {
                        "quat": [
                            0.07861328125,
                            -0.23388671875,
                            -0.04638671875,
                            1.98388671875
                        ]
                    }
                ],
                "lastFrameTime": 30
            }
        },
        {
            "boneId": 1040,
            "frameType": 1,
            "startTime": 30,
            "frames": {
                "frames": [
                    {
                        "quat": [
                            -0.67626953125,
                            -0.28125,
                            -0.15087890625,
                            1.8544921875
                        ]
                    }
                ],
                "lastFrameTime": 30
            }
        },
        {
            "boneId": 1001,
            "frameType": 1,
            "startTime": 0,
            "frames": {
                "frames": [
                    {
                        "time": 0,
                        "quat": [
                            -0.3349609375,
                            0.212890625,
                            0.177734375,
                            1.9521484375
                        ]
                    },
                    {
                        "time": 21.005859375,
                        "quat": [
                            -0.34521484375,
                            0.2099609375,
                            0.20654296875,
                            1.94775390625
                        ]
                    },
                    {
                        "time": 8.994140625,
                        "quat": [
                            -0.3349609375,
                            0.212890625,
                            0.177734375,
                            1.9521484375
                        ]
                    }
                ],
                "lastFrameTime": 8.994140625
            }
        },
        {
            "boneId": 1003,
            "frameType": 3,
            "startTime": 0,
            "frames": {
                "frames": [
                    {
                        "position": [
                            0.1318359375,
                            0.04541015625,
                            0.00146484375
                        ]
                    },
                    {
                        "time": 14.00390625,
                        "position": [
                            0.1318359375,
                            0.04541015625,
                            0.00146484375
                        ]
                    },
                    {
                        "time": 15.99609375,
                        "position": [
                            0.1318359375,
                            0.04541015625,
                            0.00146484375
                        ]
                    }
                ],
                "lastFrameTime": 15.99609375
            },
            "direction": [
                1.4638671875,
                1.36181640625,
                0.02490234375,
                0.025390625
            ]
        },
        {
            "boneId": 1039,
            "frameType": 1,
            "startTime": 0,
            "frames": {
                "frames": [
                    {
                        "time": 0,
                        "quat": [
                            0.95263671875,
                            0.16748046875,
                            0.55078125,
                            1.66162109375
                        ]
                    },
                    {
                        "time": 14.00390625,
                        "quat": [
                            0.94189453125,
                            0.16357421875,
                            0.5263671875,
                            1.67626953125
                        ]
                    },
                    {
                        "time": 15.99609375,
                        "quat": [
                            0.95263671875,
                            0.16748046875,
                            0.55078125,
                            1.66162109375
                        ]
                    }
                ],
                "lastFrameTime": 15.99609375
            }
        },
        {
            "boneId": 1020,
            "frameType": 1,
            "startTime": 0,
            "frames": {
                "frames": [
                    {
                        "time": 0,
                        "quat": [
                            0,
                            1.2646484375,
                            0,
                            1.54931640625
                        ]
                    },
                    {
                        "time": 14.00390625,
                        "quat": [
                            0,
                            1.294921875,
                            0,
                            1.52392578125
                        ]
                    },
                    {
                        "time": 15.99609375,
                        "quat": [
                            0,
                            1.2646484375,
                            0,
                            1.54931640625
                        ]
                    }
                ],
                "lastFrameTime": 15.99609375
            }
        },
        {
            "boneId": 1021,
            "frameType": 1,
            "startTime": 0,
            "frames": {
                "frames": [
                    {
                        "time": 0,
                        "quat": [
                            1.66748046875,
                            -0.6435546875,
                            -0.15087890625,
                            -0.88330078125
                        ]
                    },
                    {
                        "time": 14.00390625,
                        "quat": [
                            1.65869140625,
                            -0.63134765625,
                            -0.1884765625,
                            -0.90185546875
                        ]
                    },
                    {
                        "time": 15.99609375,
                        "quat": [
                            1.66748046875,
                            -0.6435546875,
                            -0.15087890625,
                            -0.88330078125
                        ]
                    }
                ],
                "lastFrameTime": 15.99609375
            }
        },
        {
            "boneId": 1057,
            "frameType": 3,
            "startTime": 0,
            "frames": {
                "frames": [
                    {
                        "position": [
                            0.1318359375,
                            -0.044921875,
                            0.00146484375
                        ]
                    },
                    {
                        "time": 14.00390625,
                        "position": [
                            0.1318359375,
                            -0.044921875,
                            0.00146484375
                        ]
                    },
                    {
                        "time": 15.99609375,
                        "position": [
                            0.1318359375,
                            -0.044921875,
                            0.00146484375
                        ]
                    }
                ],
                "lastFrameTime": 15.99609375
            },
            "direction": [
                -1.37890625,
                1.44677734375,
                0.04541015625,
                -0.0439453125
            ]
        },
        {
            "boneId": 1093,
            "frameType": 1,
            "startTime": 0,
            "frames": {
                "frames": [
                    {
                        "time": 0,
                        "quat": [
                            -0.107421875,
                            1.400390625,
                            -0.60693359375,
                            1.2880859375
                        ]
                    },
                    {
                        "time": 14.00390625,
                        "quat": [
                            -0.1044921875,
                            1.380859375,
                            -0.63720703125,
                            1.29443359375
                        ]
                    },
                    {
                        "time": 15.99609375,
                        "quat": [
                            -0.107421875,
                            1.400390625,
                            -0.60693359375,
                            1.2880859375
                        ]
                    }
                ],
                "lastFrameTime": 15.99609375
            }
        },
        {
            "boneId": 1074,
            "frameType": 1,
            "startTime": 0,
            "frames": {
                "frames": [
                    {
                        "time": 0,
                        "quat": [
                            0,
                            1.564453125,
                            0,
                            1.24609375
                        ]
                    },
                    {
                        "time": 14.00390625,
                        "quat": [
                            0,
                            1.58740234375,
                            0,
                            1.21630859375
                        ]
                    },
                    {
                        "time": 15.99609375,
                        "quat": [
                            0,
                            1.564453125,
                            0,
                            1.24609375
                        ]
                    }
                ],
                "lastFrameTime": 15.99609375
            }
        },
        {
            "boneId": 1075,
            "frameType": 1,
            "startTime": 30,
            "frames": {
                "frames": [
                    {
                        "quat": [
                            1.6552734375,
                            0.6142578125,
                            -0.599609375,
                            -0.72265625
                        ]
                    }
                ],
                "lastFrameTime": 30
            }
        }
    ],
    "unknown5": "00004040",
    "entry": []
}