{
    "frameTimeCount": 24.00000035762787,
    "bones": [
        {
            "boneId": 1095,
            "frameType": 1,
            "startTime": 0,
            "frames": {
                "frames": [
                    {
                        "time": 0,
                        "quat": [
                            -0.0869140625,
                            0.09326171875,
                            -0.0654296875,
                            1.99462890625
                        ]
                    },
                    {
                        "time": 2.0068359375,
                        "quat": [
                            -0.0869140625,
                            0.09326171875,
                            -0.0654296875,
                            1.99462890625
                        ]
                    },
                    {
                        "time": 2.98828125,
                        "quat": [
                            -0.09228515625,
                            0.26708984375,
                            -0.0576171875,
                            1.97900390625
                        ]
                    },
                    {
                        "time": 10.0048828125,
                        "quat": [
                            -0.083984375,
                            0.0048828125,
                            -0.06884765625,
                            1.9970703125
                        ]
                    },
                    {
                        "time": 8.994140625,
                        "quat": [
                            -0.0869140625,
                            0.09326171875,
                            -0.0654296875,
                            1.99462890625
                        ]
                    }
                ],
                "lastFrameTime": 9.000000357627869
            }
        },
        {
            "boneId": 1096,
            "frameType": 1,
            "startTime": 0,
            "frames": {
                "frames": [
                    {
                        "time": 0,
                        "quat": [
                            0.11328125,
                            0.06298828125,
                            0.02587890625,
                            1.99560546875
                        ]
                    },
                    {
                        "time": 2.0068359375,
                        "quat": [
                            0.11474609375,
                            0.2109375,
                            0.017578125,
                            1.9853515625
                        ]
                    },
                    {
                        "time": 21.9873046875,
                        "quat": [
                            0.11328125,
                            0.06298828125,
                            0.02587890625,
                            1.99560546875
                        ]
                    }
                ],
                "lastFrameTime": 21.99316442012787
            }
        },
        {
            "boneId": 1040,
            "frameType": 1,
            "startTime": 0,
            "frames": {
                "frames": [
                    {
                        "time": 0,
                        "quat": [
                            0,
                            0,
                            0.2001953125,
                            1.98974609375
                        ]
                    },
                    {
                        "time": 6.005859375,
                        "quat": [
                            0.01708984375,
                            0.17236328125,
                            0.19970703125,
                            1.982421875
                        ]
                    },
                    {
                        "time": 11.9970703125,
                        "quat": [
                            0.0087890625,
                            0.08837890625,
                            0.2001953125,
                            1.98779296875
                        ]
                    },
                    {
                        "time": 5.9912109375,
                        "quat": [
                            0,
                            0,
                            0.2001953125,
                            1.98974609375
                        ]
                    }
                ],
                "lastFrameTime": 5.997070670127869
            }
        },
        {
            "boneId": 1001,
            "frameType": 1,
            "startTime": 0,
            "frames": {
                "frames": [
                    {
                        "time": 0,
                        "quat": [
                            0.1552734375,
                            -0.47412109375,
                            0.056640625,
                            1.93603515625
                        ]
                    },
                    {
                        "time": 2.0068359375,
                        "quat": [
                            0.18408203125,
                            -0.7080078125,
                            0.00634765625,
                            1.861328125
                        ]
                    },
                    {
                        "time": 1.9921875,
                        "quat": [
                            0.21435546875,
                            -0.767578125,
                            -0.0107421875,
                            1.833984375
                        ]
                    },
                    {
                        "time": 11.0009765625,
                        "quat": [
                            0.103515625,
                            -0.51123046875,
                            0.06591796875,
                            1.9296875
                        ]
                    },
                    {
                        "time": 3.0029296875,
                        "quat": [
                            0.0986328125,
                            -0.5361328125,
                            0.068359375,
                            1.9228515625
                        ]
                    },
                    {
                        "time": 5.9912109375,
                        "quat": [
                            0.1552734375,
                            -0.47412109375,
                            0.056640625,
                            1.93603515625
                        ]
                    }
                ],
                "lastFrameTime": 5.997070670127869
            }
        },
        {
            "boneId": 1003,
            "frameType": 2,
            "startTime": 0.99609375,
            "frames": {
                "frames": [
                    {
                        "quat": [
                            1.02392578125,
                            1.5419921875,
                            -0.53369140625,
                            -0.5361328125
                        ],
                        "position": [
                            -0.015625,
                            0.02587890625,
                            0.01953125
                        ]
                    },
                    {
                        "quat": [
                            1.01171875,
                            1.5537109375,
                            -0.55615234375,
                            -0.50244140625
                        ],
                        "position": [
                            -0.0146484375,
                            0.02587890625,
                            0.0205078125
                        ]
                    },
                    {
                        "quat": [
                            1.0009765625,
                            1.5625,
                            -0.5751953125,
                            -0.47314453125
                        ],
                        "position": [
                            -0.01416015625,
                            0.02587890625,
                            0.02099609375
                        ]
                    },
                    {
                        "quat": [
                            0.99267578125,
                            1.5693359375,
                            -0.58935546875,
                            -0.4501953125
                        ],
                        "position": [
                            -0.01318359375,
                            0.02587890625,
                            0.021484375
                        ]
                    },
                    {
                        "quat": [
                            0.98486328125,
                            1.5751953125,
                            -0.60302734375,
                            -0.42919921875
                        ],
                        "position": [
                            -0.0126953125,
                            0.02587890625,
                            0.021484375
                        ]
                    },
                    {
                        "quat": [
                            0.9775390625,
                            1.58056640625,
                            -0.61474609375,
                            -0.41015625
                        ],
                        "position": [
                            -0.01220703125,
                            0.02587890625,
                            0.02197265625
                        ]
                    },
                    {
                        "quat": [
                            0.9736328125,
                            1.5830078125,
                            -0.62060546875,
                            -0.40087890625
                        ],
                        "position": [
                            -0.01220703125,
                            0.02587890625,
                            0.02197265625
                        ]
                    },
                    {
                        "quat": [
                            0.9755859375,
                            1.58154296875,
                            -0.61767578125,
                            -0.4052734375
                        ],
                        "position": [
                            -0.01220703125,
                            0.02587890625,
                            0.02197265625
                        ]
                    },
                    {
                        "quat": [
                            0.9775390625,
                            1.580078125,
                            -0.6142578125,
                            -0.41064453125
                        ],
                        "position": [
                            -0.01220703125,
                            0.02587890625,
                            0.02197265625
                        ]
                    },
                    {
                        "quat": [
                            0.9794921875,
                            1.57861328125,
                            -0.61083984375,
                            -0.416015625
                        ],
                        "position": [
                            -0.0126953125,
                            0.02587890625,
                            0.02197265625
                        ]
                    },
                    {
                        "quat": [
                            0.98193359375,
                            1.5771484375,
                            -0.607421875,
                            -0.421875
                        ],
                        "position": [
                            -0.0126953125,
                            0.02587890625,
                            0.02197265625
                        ]
                    },
                    {
                        "quat": [
                            0.98388671875,
                            1.57568359375,
                            -0.60400390625,
                            -0.42724609375
                        ],
                        "position": [
                            -0.0126953125,
                            0.02587890625,
                            0.021484375
                        ]
                    },
                    {
                        "quat": [
                            0.98583984375,
                            1.57421875,
                            -0.60107421875,
                            -0.4326171875
                        ],
                        "position": [
                            -0.0126953125,
                            0.02587890625,
                            0.021484375
                        ]
                    },
                    {
                        "quat": [
                            0.98779296875,
                            1.57275390625,
                            -0.59765625,
                            -0.43798828125
                        ],
                        "position": [
                            -0.01318359375,
                            0.02587890625,
                            0.021484375
                        ]
                    },
                    {
                        "quat": [
                            0.990234375,
                            1.5712890625,
                            -0.59423828125,
                            -0.443359375
                        ],
                        "position": [
                            -0.01318359375,
                            0.02587890625,
                            0.021484375
                        ]
                    },
                    {
                        "quat": [
                            0.9921875,
                            1.56982421875,
                            -0.5908203125,
                            -0.44873046875
                        ],
                        "position": [
                            -0.01318359375,
                            0.02587890625,
                            0.021484375
                        ]
                    },
                    {
                        "quat": [
                            0.994140625,
                            1.568359375,
                            -0.58740234375,
                            -0.4541015625
                        ],
                        "position": [
                            -0.013671875,
                            0.02587890625,
                            0.02099609375
                        ]
                    },
                    {
                        "quat": [
                            0.99609375,
                            1.56689453125,
                            -0.58349609375,
                            -0.45947265625
                        ],
                        "position": [
                            -0.013671875,
                            0.02587890625,
                            0.02099609375
                        ]
                    },
                    {
                        "quat": [
                            0.9990234375,
                            1.564453125,
                            -0.57861328125,
                            -0.46728515625
                        ],
                        "position": [
                            -0.013671875,
                            0.02587890625,
                            0.02099609375
                        ]
                    },
                    {
                        "quat": [
                            1.00341796875,
                            1.56103515625,
                            -0.57177734375,
                            -0.478515625
                        ],
                        "position": [
                            -0.01416015625,
                            0.02587890625,
                            0.0205078125
                        ]
                    },
                    {
                        "quat": [
                            1.00732421875,
                            1.5576171875,
                            -0.56396484375,
                            -0.490234375
                        ],
                        "position": [
                            -0.0146484375,
                            0.02587890625,
                            0.0205078125
                        ]
                    },
                    {
                        "quat": [
                            1.01171875,
                            1.5537109375,
                            -0.556640625,
                            -0.50146484375
                        ],
                        "position": [
                            -0.0146484375,
                            0.02587890625,
                            0.0205078125
                        ]
                    },
                    {
                        "quat": [
                            1.015625,
                            1.5498046875,
                            -0.54931640625,
                            -0.51318359375
                        ],
                        "position": [
                            -0.01513671875,
                            0.02587890625,
                            0.02001953125
                        ]
                    },
                    {
                        "quat": [
                            1.02001953125,
                            1.5458984375,
                            -0.54150390625,
                            -0.52490234375
                        ],
                        "position": [
                            -0.01513671875,
                            0.02587890625,
                            0.02001953125
                        ]
                    },
                    {
                        "quat": [
                            1.02392578125,
                            1.5419921875,
                            -0.53369140625,
                            -0.5361328125
                        ],
                        "position": [
                            -0.015625,
                            0.02587890625,
                            0.01953125
                        ]
                    }
                ],
                "lastFrameTime": 1.0898441076278687
            }
        },
        {
            "boneId": 1039,
            "frameType": 1,
            "startTime": 0,
            "frames": {
                "frames": [
                    {
                        "time": 0,
                        "quat": [
                            0.45654296875,
                            0.6123046875,
                            0.4091796875,
                            1.802734375
                        ]
                    },
                    {
                        "time": 0.99609375,
                        "quat": [
                            0.50341796875,
                            0.58349609375,
                            0.3720703125,
                            1.8076171875
                        ]
                    },
                    {
                        "time": 1.0107421875,
                        "quat": [
                            0.48974609375,
                            0.58349609375,
                            0.39404296875,
                            1.806640625
                        ]
                    },
                    {
                        "time": 2.98828125,
                        "quat": [
                            0.361328125,
                            0.50390625,
                            0.58837890625,
                            1.80810546875
                        ]
                    },
                    {
                        "time": 7.001953125,
                        "quat": [
                            0.31982421875,
                            0.50146484375,
                            0.50634765625,
                            1.84130859375
                        ]
                    },
                    {
                        "time": 3.0029296875,
                        "quat": [
                            0.3876953125,
                            0.541015625,
                            0.404296875,
                            1.841796875
                        ]
                    },
                    {
                        "time": 4.9951171875,
                        "quat": [
                            0.4189453125,
                            0.54541015625,
                            0.40087890625,
                            1.83447265625
                        ]
                    },
                    {
                        "time": 3.9990234375,
                        "quat": [
                            0.4443359375,
                            0.61376953125,
                            0.3974609375,
                            1.8076171875
                        ]
                    }
                ],
                "lastFrameTime": 4.004883170127869
            }
        },
        {
            "boneId": 1020,
            "frameType": 1,
            "startTime": 0,
            "frames": {
                "frames": [
                    {
                        "time": 0,
                        "quat": [
                            0,
                            0.84814453125,
                            0,
                            1.8115234375
                        ]
                    },
                    {
                        "time": 0.99609375,
                        "quat": [
                            0,
                            1.1005859375,
                            0,
                            1.669921875
                        ]
                    },
                    {
                        "time": 3.0029296875,
                        "quat": [
                            0,
                            1.34423828125,
                            0,
                            1.48095703125
                        ]
                    },
                    {
                        "time": 0.99609375,
                        "quat": [
                            0,
                            1.36181640625,
                            0,
                            1.46484375
                        ]
                    },
                    {
                        "time": 6.005859375,
                        "quat": [
                            0,
                            0.990234375,
                            0,
                            1.73779296875
                        ]
                    },
                    {
                        "time": 0.99609375,
                        "quat": [
                            0,
                            0.96240234375,
                            0,
                            1.75341796875
                        ]
                    },
                    {
                        "time": 7.998046875,
                        "quat": [
                            0,
                            0.97802734375,
                            0,
                            1.74462890625
                        ]
                    },
                    {
                        "time": 3.9990234375,
                        "quat": [
                            0,
                            0.84814453125,
                            0,
                            1.8115234375
                        ]
                    }
                ],
                "lastFrameTime": 4.004883170127869
            }
        },
        {
            "boneId": 1021,
            "frameType": 1,
            "startTime": 0,
            "frames": {
                "frames": [
                    {
                        "time": 0,
                        "quat": [
                            1.93212890625,
                            -0.16845703125,
                            -0.2724609375,
                            0.40576171875
                        ]
                    },
                    {
                        "time": 0.99609375,
                        "quat": [
                            1.85595703125,
                            -0.07763671875,
                            -0.3349609375,
                            0.66162109375
                        ]
                    },
                    {
                        "time": 3.0029296875,
                        "quat": [
                            1.7744140625,
                            0.12841796875,
                            -0.26416015625,
                            0.875
                        ]
                    },
                    {
                        "time": 0.99609375,
                        "quat": [
                            1.77001953125,
                            0.16015625,
                            -0.2451171875,
                            0.8837890625
                        ]
                    },
                    {
                        "time": 3.0029296875,
                        "quat": [
                            1.87646484375,
                            0.0849609375,
                            -0.296875,
                            0.619140625
                        ]
                    },
                    {
                        "time": 3.0029296875,
                        "quat": [
                            1.9296875,
                            -0.0810546875,
                            -0.3505859375,
                            0.38330078125
                        ]
                    },
                    {
                        "time": 0.99609375,
                        "quat": [
                            1.93212890625,
                            -0.12841796875,
                            -0.3671875,
                            0.34033203125
                        ]
                    },
                    {
                        "time": 3.0029296875,
                        "quat": [
                            1.921875,
                            -0.16650390625,
                            -0.40283203125,
                            0.3408203125
                        ]
                    },
                    {
                        "time": 4.9951171875,
                        "quat": [
                            1.91552734375,
                            -0.17724609375,
                            -0.4072265625,
                            0.36376953125
                        ]
                    },
                    {
                        "time": 3.9990234375,
                        "quat": [
                            1.93603515625,
                            -0.16357421875,
                            -0.2724609375,
                            0.38916015625
                        ]
                    }
                ],
                "lastFrameTime": 4.004883170127869
            }
        },
        {
            "boneId": 1057,
            "frameType": 2,
            "startTime": 0.99609375,
            "frames": {
                "frames": [
                    {
                        "quat": [
                            1.41943359375,
                            -1.40771484375,
                            -0.0302734375,
                            0.021484375
                        ],
                        "position": [
                            -0.00439453125,
                            -0.02978515625,
                            0.01953125
                        ]
                    },
                    {
                        "quat": [
                            1.419921875,
                            -1.40625,
                            0.01953125,
                            -0.06298828125
                        ],
                        "position": [
                            -0.00341796875,
                            -0.02978515625,
                            0.02001953125
                        ]
                    },
                    {
                        "quat": [
                            1.42041015625,
                            -1.4033203125,
                            0.0224609375,
                            -0.109375
                        ],
                        "position": [
                            -0.00244140625,
                            -0.02978515625,
                            0.02001953125
                        ]
                    },
                    {
                        "quat": [
                            1.42041015625,
                            -1.39990234375,
                            0.0234375,
                            -0.14404296875
                        ],
                        "position": [
                            -0.001953125,
                            -0.02978515625,
                            0.02001953125
                        ]
                    },
                    {
                        "quat": [
                            1.4208984375,
                            -1.39599609375,
                            0.0224609375,
                            -0.1748046875
                        ],
                        "position": [
                            -0.00146484375,
                            -0.02978515625,
                            0.02001953125
                        ]
                    },
                    {
                        "quat": [
                            1.42138671875,
                            -1.392578125,
                            0.01416015625,
                            -0.197265625
                        ],
                        "position": [
                            -0.0009765625,
                            -0.02978515625,
                            0.02001953125
                        ]
                    },
                    {
                        "quat": [
                            1.42138671875,
                            -1.39208984375,
                            0.00048828125,
                            -0.2021484375
                        ],
                        "position": [
                            -0.0009765625,
                            -0.02978515625,
                            0.02001953125
                        ]
                    },
                    {
                        "quat": [
                            1.4208984375,
                            -1.3935546875,
                            -0.001953125,
                            -0.19384765625
                        ],
                        "position": [
                            -0.0009765625,
                            -0.02978515625,
                            0.02001953125
                        ]
                    },
                    {
                        "quat": [
                            1.4208984375,
                            -1.39453125,
                            -0.00439453125,
                            -0.18408203125
                        ],
                        "position": [
                            -0.0009765625,
                            -0.02978515625,
                            0.02001953125
                        ]
                    },
                    {
                        "quat": [
                            1.4208984375,
                            -1.39599609375,
                            -0.00634765625,
                            -0.1748046875
                        ],
                        "position": [
                            -0.0009765625,
                            -0.02978515625,
                            0.02001953125
                        ]
                    },
                    {
                        "quat": [
                            1.4208984375,
                            -1.3974609375,
                            -0.0087890625,
                            -0.1650390625
                        ],
                        "position": [
                            -0.00146484375,
                            -0.02978515625,
                            0.02001953125
                        ]
                    },
                    {
                        "quat": [
                            1.42041015625,
                            -1.39892578125,
                            -0.01123046875,
                            -0.1552734375
                        ],
                        "position": [
                            -0.00146484375,
                            -0.02978515625,
                            0.02001953125
                        ]
                    },
                    {
                        "quat": [
                            1.42041015625,
                            -1.39990234375,
                            -0.01611328125,
                            -0.14404296875
                        ],
                        "position": [
                            -0.00146484375,
                            -0.02978515625,
                            0.02001953125
                        ]
                    },
                    {
                        "quat": [
                            1.419921875,
                            -1.40185546875,
                            -0.02490234375,
                            -0.13037109375
                        ],
                        "position": [
                            -0.001953125,
                            -0.02978515625,
                            0.02001953125
                        ]
                    },
                    {
                        "quat": [
                            1.41943359375,
                            -1.40283203125,
                            -0.0341796875,
                            -0.11572265625
                        ],
                        "position": [
                            -0.001953125,
                            -0.02978515625,
                            0.02001953125
                        ]
                    },
                    {
                        "quat": [
                            1.41943359375,
                            -1.404296875,
                            -0.0439453125,
                            -0.1015625
                        ],
                        "position": [
                            -0.001953125,
                            -0.02978515625,
                            0.02001953125
                        ]
                    },
                    {
                        "quat": [
                            1.4189453125,
                            -1.4052734375,
                            -0.05322265625,
                            -0.08740234375
                        ],
                        "position": [
                            -0.001953125,
                            -0.02978515625,
                            0.02001953125
                        ]
                    },
                    {
                        "quat": [
                            1.41845703125,
                            -1.40625,
                            -0.0625,
                            -0.07275390625
                        ],
                        "position": [
                            -0.00244140625,
                            -0.02978515625,
                            0.02001953125
                        ]
                    },
                    {
                        "quat": [
                            1.41796875,
                            -1.40673828125,
                            -0.06982421875,
                            -0.05615234375
                        ],
                        "position": [
                            -0.00244140625,
                            -0.02978515625,
                            0.02001953125
                        ]
                    },
                    {
                        "quat": [
                            1.41796875,
                            -1.40771484375,
                            -0.07373046875,
                            -0.03662109375
                        ],
                        "position": [
                            -0.0029296875,
                            -0.02978515625,
                            0.02001953125
                        ]
                    },
                    {
                        "quat": [
                            1.41796875,
                            -1.40771484375,
                            -0.07275390625,
                            -0.02001953125
                        ],
                        "position": [
                            -0.0029296875,
                            -0.02978515625,
                            0.02001953125
                        ]
                    },
                    {
                        "quat": [
                            1.41845703125,
                            -1.40771484375,
                            -0.06298828125,
                            -0.0087890625
                        ],
                        "position": [
                            -0.00341796875,
                            -0.02978515625,
                            0.02001953125
                        ]
                    },
                    {
                        "quat": [
                            1.4189453125,
                            -1.408203125,
                            -0.05224609375,
                            0.0009765625
                        ],
                        "position": [
                            -0.00341796875,
                            -0.02978515625,
                            0.01953125
                        ]
                    },
                    {
                        "quat": [
                            1.41943359375,
                            -1.40771484375,
                            -0.04150390625,
                            0.01123046875
                        ],
                        "position": [
                            -0.00390625,
                            -0.02978515625,
                            0.01953125
                        ]
                    },
                    {
                        "quat": [
                            1.41943359375,
                            -1.40771484375,
                            -0.0302734375,
                            0.021484375
                        ],
                        "position": [
                            -0.00439453125,
                            -0.02978515625,
                            0.01953125
                        ]
                    }
                ],
                "lastFrameTime": 1.0898441076278687
            }
        },
        {
            "boneId": 1093,
            "frameType": 1,
            "startTime": 0,
            "frames": {
                "frames": [
                    {
                        "time": 0,
                        "quat": [
                            -0.28076171875,
                            1.12939453125,
                            -0.6142578125,
                            1.505859375
                        ]
                    },
                    {
                        "time": 0.99609375,
                        "quat": [
                            -0.248046875,
                            1.1328125,
                            -0.60791015625,
                            1.51171875
                        ]
                    },
                    {
                        "time": 1.0107421875,
                        "quat": [
                            -0.22607421875,
                            1.07763671875,
                            -0.64697265625,
                            1.5390625
                        ]
                    },
                    {
                        "time": 1.9921875,
                        "quat": [
                            -0.1015625,
                            0.9248046875,
                            -0.7421875,
                            1.60693359375
                        ]
                    },
                    {
                        "time": 0.99609375,
                        "quat": [
                            -0.0654296875,
                            0.888671875,
                            -0.76611328125,
                            1.6181640625
                        ]
                    },
                    {
                        "time": 7.001953125,
                        "quat": [
                            -0.1533203125,
                            1.15673828125,
                            -0.724609375,
                            1.45361328125
                        ]
                    },
                    {
                        "time": 3.0029296875,
                        "quat": [
                            -0.24072265625,
                            1.1630859375,
                            -0.6650390625,
                            1.46484375
                        ]
                    },
                    {
                        "time": 4.9951171875,
                        "quat": [
                            -0.2666015625,
                            1.0966796875,
                            -0.6298828125,
                            1.52587890625
                        ]
                    },
                    {
                        "time": 3.9990234375,
                        "quat": [
                            -0.28076171875,
                            1.12939453125,
                            -0.6142578125,
                            1.505859375
                        ]
                    }
                ],
                "lastFrameTime": 4.004883170127869
            }
        },
        {
            "boneId": 1074,
            "frameType": 1,
            "startTime": 0,
            "frames": {
                "frames": [
                    {
                        "time": 0,
                        "quat": [
                            0,
                            0.7314453125,
                            0,
                            1.861328125
                        ]
                    },
                    {
                        "time": 0.99609375,
                        "quat": [
                            0,
                            0.94482421875,
                            0,
                            1.7626953125
                        ]
                    },
                    {
                        "time": 3.0029296875,
                        "quat": [
                            0,
                            1.2822265625,
                            0,
                            1.53515625
                        ]
                    },
                    {
                        "time": 0.99609375,
                        "quat": [
                            0,
                            1.31298828125,
                            0,
                            1.5087890625
                        ]
                    },
                    {
                        "time": 6.005859375,
                        "quat": [
                            0,
                            0.76171875,
                            0,
                            1.84912109375
                        ]
                    },
                    {
                        "time": 0.99609375,
                        "quat": [
                            0,
                            0.7060546875,
                            0,
                            1.87109375
                        ]
                    },
                    {
                        "time": 7.998046875,
                        "quat": [
                            0,
                            0.826171875,
                            0,
                            1.8212890625
                        ]
                    },
                    {
                        "time": 3.9990234375,
                        "quat": [
                            0,
                            0.7314453125,
                            0,
                            1.861328125
                        ]
                    }
                ],
                "lastFrameTime": 4.004883170127869
            }
        },
        {
            "boneId": 1075,
            "frameType": 1,
            "startTime": 0,
            "frames": {
                "frames": [
                    {
                        "time": 0,
                        "quat": [
                            1.7314453125,
                            0.1474609375,
                            -0.52001953125,
                            -0.841796875
                        ]
                    },
                    {
                        "time": 0.99609375,
                        "quat": [
                            1.7529296875,
                            -0.11181640625,
                            -0.46630859375,
                            -0.83447265625
                        ]
                    },
                    {
                        "time": 3.0029296875,
                        "quat": [
                            -1.58447265625,
                            0.34765625,
                            0.4521484375,
                            1.078125
                        ]
                    },
                    {
                        "time": 0.99609375,
                        "quat": [
                            -1.55517578125,
                            0.357421875,
                            0.45263671875,
                            1.1171875
                        ]
                    },
                    {
                        "time": 3.9990234375,
                        "quat": [
                            1.68017578125,
                            -0.03076171875,
                            -0.4736328125,
                            -0.974609375
                        ]
                    },
                    {
                        "time": 3.0029296875,
                        "quat": [
                            1.73095703125,
                            0.1845703125,
                            -0.482421875,
                            -0.8583984375
                        ]
                    },
                    {
                        "time": 7.998046875,
                        "quat": [
                            1.72705078125,
                            0.22021484375,
                            -0.53955078125,
                            -0.822265625
                        ]
                    },
                    {
                        "time": 3.9990234375,
                        "quat": [
                            1.7314453125,
                            0.1474609375,
                            -0.52001953125,
                            -0.841796875
                        ]
                    }
                ],
                "lastFrameTime": 4.004883170127869
            }
        }
    ],
    "unknown5": "00004040",
    "entry": []
}